Workbook
Name anos_taxa: 'Escolha do Perfil'!$E$20
Name anos_taxa: Planilha1!$E$20
Name dividendos_mensais: 'Escolha do Perfil'!$E$23
Name dividendos_mensais: Planilha1!$E$23
Name Investimento_mensal: 'Escolha do Perfil'!$E$19
Name Investimento_mensal: Planilha1!$E$19
Name patrimonio_acumulado: 'Escolha do Perfil'!$E$22
Name patrimonio_acumulado: Planilha1!$E$22
Name rendimento_carteira: 'Escolha do Perfil'!$E$15
Name rendimento_carteira: Planilha1!$E$15
Name salario: 'Escolha do Perfil'!$E$14
Name salario: Planilha1!$E$14
Name sugestao_de_investimento: 'Escolha do Perfil'!$E$16
Name sugestao_de_investimento: Planilha1!$E$16
Name Taxa_Rendimento_Mensal: 'Escolha do Perfil'!$E$21
Name Taxa_Rendimento_Mensal: Planilha1!$E$21

Sheet Escolha do Perfil
B13: CONFIGURAÇÕES
B14: Salário | E14: 2000
B15: Rendimento Carteira | E15: 0.006
B16: Sugestão de Investimento | E16: =$E$14*30% -> 600
B18: INVESTIMENTO MENSAL
B19: Quanto investir por mês? | E19: 200
B20: Por Quantos Anos? | E20: 5
B21: Taxa de Rendimento Mensal? | E21: 0.01079
B22: Patrimônio Acumulado? | E22: =FV($E$21,($E$20*12),($E$19*-1)) -> 16755.383
B23: Dividendos Mensais? | E23: =E22*1% -> 167.55383
B25: CENÁRIOS | E25: DIVIDENDOS
A26: 2 | B26: Quanto em 2 Anos? | D26: =FV($E$21,(A26*12),($E$19*-1)) -> 5445.5255 | E26: =D26*$E$15 -> 32.673153
A27: 5 | B27: Quanto em 5 Anos? | D27: =FV($E$21,(A27*12),($E$19*-1)) -> 16755.383 | E27: =D27*$E$15 -> 100.5323
A28: 10 | B28: Quanto em 10 Anos? | D28: =FV($E$21,(A28*12),($E$19*-1)) -> 48656.843 | E28: =D28*$E$15 -> 291.94106
A29: 20 | B29: Quanto em 20 Anos? | D29: =FV($E$21,(A29*12),($E$19*-1)) -> 225039.68 | E29: =D29*$E$15 -> 1350.2381
A30: 30 | B30: Quanto em 30 Anos? | D30: =FV($E$21,(A30*12),($E$19*-1)) -> 864433.93 | E30: =D30*$E$15 -> 5186.6036
B32: PERFIL | D32: AGRESSIVO
B33: VALOR A SER INVESTIDO POR MÊS | D33: =Investimento_mensal -> 200
B35: TIPO DE FII | C35: PERCENTUAL SUGERIDO | D35: VALORES
B36: PAPEL | C36: =VLOOKUP($D$32&"-"&B36,Planilha3!A:D,4,0) -> 0.5 | D36: =$D$33*C36 -> 100
B37: TIJOLO | C37: =VLOOKUP($D$32&"-"&B37,Planilha3!A:D,4,0) -> 0.1 | D37: =$D$33*C37 -> 20
B38: HIBRIDOS | C38: =VLOOKUP($D$32&"-"&B38,Planilha3!A:D,4,0) -> 0.05 | D38: =$D$33*C38 -> 10
B39: FOF's | C39: =VLOOKUP($D$32&"-"&B39,Planilha3!A:D,4,0) -> 0.05 | D39: =$D$33*C39 -> 10
B40: DESENVOLVIMENTO | C40: =VLOOKUP($D$32&"-"&B40,Planilha3!A:D,4,0) -> 0.2 | D40: =$D$33*C40 -> 40
B41: HOTELARIAS | C41: =VLOOKUP($D$32&"-"&B41,Planilha3!A:D,4,0) -> 0.1 | D41: =$D$33*C41 -> 20
D42: =SUM(D36:D41) -> 200

Sheet Planilha1
B13: CONFIGURAÇÕES
B14: Salário | E14: 5000
B15: Rendimento Carteira | E15: 0.01
B16: Sugestão de Investimento | E16: =$E$14*30% -> 1500
B18: INVESTIMENTO MENSAL
B19: Quanto investir por mês? | E19: 500
B20: Por Quantos Anos? | E20: 5
B21: Taxa de Rendimento Mensal? | E21: 0.01079
B22: Patrimônio Acumulado? | E22: =FV($E$21,($E$20*12),($E$19*-1)) -> 41888.457
B23: Dividendos Mensais? | E23: =E22*1% -> 418.88457
B25: CENÁRIOS | E25: DIVIDENDOS
A26: 2 | B26: Quanto em 2 Anos? | D26: =FV($E$21,(A26*12),($E$19*-1)) -> 13613.814 | E26: =D26*$E$15 -> 136.13814
A27: 5 | B27: Quanto em 5 Anos? | D27: =FV($E$21,(A27*12),($E$19*-1)) -> 41888.457 | E27: =D27*$E$15 -> 418.88457
A28: 10 | B28: Quanto em 10 Anos? | D28: =FV($E$21,(A28*12),($E$19*-1)) -> 121642.11 | E28: =D28*$E$15 -> 1216.4211
A29: 20 | B29: Quanto em 20 Anos? | D29: =FV($E$21,(A29*12),($E$19*-1)) -> 562599.2 | E29: =D29*$E$15 -> 5625.992
A30: 30 | B30: Quanto em 30 Anos? | D30: =FV($E$21,(A30*12),($E$19*-1)) -> 2161084.8 | E30: =D30*$E$15 -> 21610.848

Sheet Planilha3
A2: CHAVE | B2: PERFIL | C2: TIPO FII | D2: PERCENTUAL SUGERIDO
A3: =B3&"-"&C3 -> CONSERVADOR-PAPEL | B3: CONSERVADOR | C3: PAPEL | D3: 0.3
A4: =B4&"-"&C4 -> CONSERVADOR-TIJOLO | B4: CONSERVADOR | C4: TIJOLO | D4: 0.5
A5: =B5&"-"&C5 -> CONSERVADOR-HIBRIDOS | B5: CONSERVADOR | C5: HIBRIDOS | D5: 0.1
A6: =B6&"-"&C6 -> CONSERVADOR-FOF's | B6: CONSERVADOR | C6: FOF's | D6: 0.1
A7: =B7&"-"&C7 -> CONSERVADOR-DESENVOLVIMENTO | B7: CONSERVADOR | C7: DESENVOLVIMENTO | D7: 0
A8: =B8&"-"&C8 -> CONSERVADOR-HOTELARIAS | B8: CONSERVADOR | C8: HOTELARIAS | D8: 0
A9: =B9&"-"&C9 -> MODERADO-PAPEL | B9: MODERADO | C9: PAPEL | D9: 0.32
A10: =B10&"-"&C10 -> MODERADO-TIJOLO | B10: MODERADO | C10: TIJOLO | D10: 0.4
A11: =B11&"-"&C11 -> MODERADO-HIBRIDOS | B11: MODERADO | C11: HIBRIDOS | D11: 0.08
A12: =B12&"-"&C12 -> MODERADO-FOF's | B12: MODERADO | C12: FOF's | D12: 0.1
A13: =B13&"-"&C13 -> MODERADO-DESENVOLVIMENTO | B13: MODERADO | C13: DESENVOLVIMENTO | D13: 0.05
A14: =B14&"-"&C14 -> MODERADO-HOTELARIAS | B14: MODERADO | C14: HOTELARIAS | D14: 0.05
... A20: =B20&"-"&C20 -> AGRESSIVO-HOTELARIAS | B20: AGRESSIVO | C20: HOTELARIAS | D20: 0.1
